{
  "id": "history.bitcoin-anarchism",
  "title": "Bitcoin and Anarchism",
  "description": "Bitcoin governance is not a voting democracy; validity is enforced by voluntary rule-following nodes rather than ballots. This aligns with anarchist and cypherpunk ideas about non-coercive coordination.",
  "category": "History & Governance",
  "prerequisites": [
    "fundamentals.censorship-resistance"
  ],
  "resources": [
    {
      "type": "article",
      "title": "The Crypto Anarchist Manifesto",
      "url": "https://www.cypherpunkbooks.com/book/the-crypto-anarchist-manifesto",
      "notes": "Cypherpunk Library source page anchoring the manifesto inside the broader canon that shaped Bitcoin's non-coercive governance ethos."
    },
    {
      "type": "article",
      "title": "The Crypto Anarchist Manifesto",
      "url": "https://nakamotoinstitute.org/library/crypto-anarchist-manifesto/",
      "notes": "Foundational cypherpunk framing for non-state digital coordination."
    },
    {
      "type": "article",
      "title": "BIP 148: UASF SegWit Activation",
      "url": "https://github.com/bitcoin/bips/blob/master/bip-0148.mediawiki",
      "notes": "Practical case where rule enforcement came from node operators."
    },
    {
      "type": "book",
      "title": "The Book of Satoshi",
      "url": "https://amzn.to/4lvhhQ8",
      "notes": "Primary-source writing that helps anchor the historical and philosophical context around this topic.",
      "regionalUrls": {
        "BR": "https://amzn.to/3NWFpyF"
      }
    }
  ],
  "estimatedTime": "45m",
  "tags": [
    "history",
    "governance"
  ],
  "aliases": [
    "bitcoin is not democracy",
    "anarchism and bitcoin",
    "crypto anarchist manifesto"
  ]
}
