{
  "id": "ops.tor-node-connections",
  "title": "Tor for Node Connectivity",
  "description": "Improving network privacy and resilience by routing node traffic over Tor.",
  "category": "Network, Relay & Client Sync",
  "prerequisites": [
    "privacy.network-privacy"
  ],
  "resources": [
    {
      "type": "article",
      "title": "Bitcoin Core Tor Documentation",
      "url": "https://github.com/bitcoin/bitcoin/blob/master/doc/tor.md",
      "notes": "Canonical node configuration guidance for Tor."
    },
    {
      "type": "book",
      "title": "Mastering Bitcoin",
      "url": "https://amzn.to/4ro0NdG",
      "notes": "Broad technical reference for the wallet, transaction, and protocol ideas that support this topic.",
      "regionalUrls": {
        "BR": "https://amzn.to/4te47JX"
      }
    },
    {
      "type": "article",
      "title": "Bitcoin Developer Guide: P2P Network",
      "url": "https://developer.bitcoin.org/devguide/p2p_network.html",
      "notes": "Networking foundations for peer transport choices."
    }
  ],
  "estimatedTime": "55m",
  "tags": [
    "node",
    "privacy"
  ],
  "aliases": [
    "tor nodes"
  ]
}
